{
    "name": "Area",
    "exponents": [
        {
        },
        {
        },
        {
        },
        {
        },
        {
        },
        {
        },
        {
        }
    ],
    "default unit": "SquareMeter",
    "units": [
        {
            "Length": 15
        },
        {
            "Length": 11
        },
        {
            "Length": 15
        },
        {
            "Length": 16
        },
        {
            "Length": 16
        },
        {
            "Length": 16
        },
        {
            "Length": 10
        },
        {
            "Length": 10
        },
        {
            "Length": 10
        },
        {
            "Length": 18
        },
        {
            "Length": 10
        },
        {
            "Length": 4
        },
        {
            "Length": 7
        },
        {
            "Length": 18
        }
    ],
    "conversion functions": [
        {
            "Key": "SquareKilometer",
            "Value": "x * 1e6"
        },
        {
            "Key": "SquareMeter",
            "Value": "x"
        },
        {
            "Key": "SquareDecimeter",
            "Value": "x * 1e-2"
        },
        {
            "Key": "SquareCentimeter",
            "Value": "x * 1e-4"
        },
        {
            "Key": "SquareMillimeter",
            "Value": "x * 1e-6"
        },
        {
            "Key": "SquareMicrometer",
            "Value": "x * 1e-12"
        },
        {
            "Key": "SquareMile",
            "Value": "x * 1609.344 * 1609.344"
        },
        {
            "Key": "SquareYard",
            "Value": "x * 0.9144 * 0.9144"
        },
        {
            "Key": "SquareFoot",
            "Value": "x * 9.290304e-2"
        },
        {
            "Key": "UsSurveySquareFoot",
            "Value": "x * (1200.0 / 3937.0) * (1200.0 / 3937.0)"
        },
        {
            "Key": "SquareInch",
            "Value": "x * 0.00064516"
        },
        {
            "Key": "Acre",
            "Value": "x * 4046.8564224"
        },
        {
            "Key": "Hectare",
            "Value": "x * 1e4"
        },
        {
            "Key": "SquareNauticalMile",
            "Value": "x * 3429904"
        }
    ],
    "symbols": [
        {
            "Key": "SquareKilometer",
            "Value": " "km²" "
        },
        {
            "Key": "SquareMeter",
            "Value": " "m²" "
        },
        {
            "Key": "SquareDecimeter",
            "Value": " "dm²" "
        },
        {
            "Key": "SquareCentimeter",
            "Value": " "cm²" "
        },
        {
            "Key": "SquareMillimeter",
            "Value": " "mm²" "
        },
        {
            "Key": "SquareMicrometer",
            "Value": " "µm²" "
        },
        {
            "Key": "SquareMile",
            "Value": " "mi²" "
        },
        {
            "Key": "SquareYard",
            "Value": " "yd²" "
        },
        {
            "Key": "SquareFoot",
            "Value": " "ft²" "
        },
        {
            "Key": "UsSurveySquareFoot",
            "Value": " "ft² (US)" "
        },
        {
            "Key": "SquareInch",
            "Value": " "in²" "
        },
        {
            "Key": "Acre",
            "Value": " "ac" "
        },
        {
            "Key": "Hectare",
            "Value": " "ha" "
        },
        {
            "Key": "SquareNauticalMile",
            "Value": " "nmi²" "
        }
    ],
    "plural symbols": [
    ]
}