{
    "name": "CoefficientOfThermalExpansion",
    "exponents": [
        {
        },
        {
        },
        {
        },
        {
        },
        {
        },
        {
        },
        {
        }
    ],
    "default unit": "InverseKelvin",
    "units": [
        {
            "Length": 13
        },
        {
            "Length": 20
        },
        {
            "Length": 23
        }
    ],
    "conversion functions": [
        {
            "Key": "InverseKelvin",
            "Value": "x"
        },
        {
            "Key": "InverseDegreeCelsius",
            "Value": "x"
        },
        {
            "Key": "InverseDegreeFahrenheit",
            "Value": "x * 9 / 5"
        }
    ],
    "symbols": [
        {
            "Key": "InverseKelvin",
            "Value": " "K⁻¹""
        },
        {
            "Key": "InverseDegreeCelsius",
            "Value": " "°C⁻¹""
        },
        {
            "Key": "InverseDegreeFahrenheit",
            "Value": " "°F⁻¹""
        }
    ],
    "plural symbols": [
        {
            "Key": "InverseKelvin",
            "Value": " "1/K" "
        },
        {
            "Key": "InverseDegreeCelsius",
            "Value": " "1/°C" "
        },
        {
            "Key": "InverseDegreeFahrenheit",
            "Value": " "1/°F" "
        }
    ]
}