{
    "name": "LuminousIntensity",
    "exponents": [
        {
        },
        {
        },
        {
        },
        {
        },
        {
        },
        {
        },
        {
        }
    ],
    "default unit": "Candela",
    "units": [
        {
            "Length": 7
        }
    ],
    "conversion functions": [
        {
            "Key": "Candela",
            "Value": "x"
        }
    ],
    "symbols": [
        {
            "Key": "Candela",
            "Value": " "cd" "
        }
    ],
    "plural symbols": [
    ]
}