{"name":"ElectricPotentialChangeRate","exponents":[2,1,-4,-1,0,0,0],"default unit":"VoltPerSecond","units":["VoltPerMicrosecond","VoltPerMinute","VoltPerHour","Yottavoltpersecond","Zettavoltpersecond","Exavoltpersecond","Petavoltpersecond","Teravoltpersecond","Gigavoltpersecond","Megavoltpersecond","Kilovoltpersecond","Hectovoltpersecond","Dekavoltpersecond","VoltPerSecond","Decivoltpersecond","Centivoltpersecond","Millivoltpersecond","Microvoltpersecond","Nanovoltpersecond","Picovoltpersecond","Femtovoltpersecond","Attovoltpersecond","Zeptovoltpersecond","Yoctovoltpersecond"],"conversion functions":{"VoltPerMicrosecond":"x * 1E6","VoltPerMinute":"x / 60","VoltPerHour":"x / 3600","Yottavoltpersecond":"x * 1e24","Zettavoltpersecond":"x * 1e21","Exavoltpersecond":"x * 1e18","Petavoltpersecond":"x * 1e15","Teravoltpersecond":"x * 1e12","Gigavoltpersecond":"x * 1e9","Megavoltpersecond":"x * 1e6","Kilovoltpersecond":"x * 1e3","Hectovoltpersecond":"x * 1e2","Dekavoltpersecond":"x * 1e1","VoltPerSecond":"x * 1e0","Decivoltpersecond":"x * 1e-1","Centivoltpersecond":"x * 1e-2","Millivoltpersecond":"x * 1e-3","Microvoltpersecond":"x * 1e-6","Nanovoltpersecond":"x * 1e-9","Picovoltpersecond":"x * 1e-12","Femtovoltpersecond":"x * 1e-15","Attovoltpersecond":"x * 1e-18","Zeptovoltpersecond":"x * 1e-21","Yoctovoltpersecond":"x * 1e-24"},"symbols":{"VoltPerMicrosecond":"V/μs","VoltPerMinute":"V/min","VoltPerHour":"V/h","Yottavoltpersecond":"YV/s","Zettavoltpersecond":"ZV/s","Exavoltpersecond":"EV/s","Petavoltpersecond":"PV/s","Teravoltpersecond":"TV/s","Gigavoltpersecond":"GV/s","Megavoltpersecond":"MV/s","Kilovoltpersecond":"kV/s","Hectovoltpersecond":"hV/s","Dekavoltpersecond":"daV/s","VoltPerSecond":"V/s","Decivoltpersecond":"dV/s","Centivoltpersecond":"cV/s","Millivoltpersecond":"mV/s","Microvoltpersecond":"µV/s","Nanovoltpersecond":"nV/s","Picovoltpersecond":"pV/s","Femtovoltpersecond":"fV/s","Attovoltpersecond":"aV/s","Zeptovoltpersecond":"zV/s","Yoctovoltpersecond":"yV/s"},"plural symbols":{}}